model2src/__init__.py
model2src/converted_model.py
model2src/model2src.py
model2src/strs.py
model2src/version.py
model2src-0.0.1.dist-info/METADATA
model2src-0.0.1.dist-info/WHEEL
model2src-0.0.1.dist-info/top_level.txt
model2src-0.0.1.dist-info/RECORD
